kernel_run.py
frontend/.gitignore
frontend/README.md
frontend/__init__.py
frontend/eslint.config.mjs
frontend/next-env.d.ts
frontend/next.config.mjs
frontend/next.config.ts
frontend/package-lock.json
frontend/package.json
frontend/postcss.config.mjs
frontend/styling_README.md
frontend/tailwind.config.ts
frontend/tsconfig.json
frontend/app/favicon.ico
frontend/app/globals.css
frontend/app/layout.tsx
frontend/app/page.tsx
frontend/components/Notebook.tsx
frontend/components/cell/AddCellButton.tsx
frontend/components/cell/CellButton.tsx
frontend/components/cell/MonacoCell.tsx
frontend/components/layout/ConnectionBanner.tsx
frontend/components/layout/Sidebar.tsx
frontend/components/modals/ConfirmModal.tsx
frontend/components/modals/ErrorModal.tsx
frontend/components/modals/SuccessModal.tsx
frontend/components/output/CellOutput.tsx
frontend/components/output/ErrorDisplay.tsx
frontend/components/output/MarkdownRenderer.tsx
frontend/components/popups/ComputePopup.tsx
frontend/components/popups/FilterPopup.tsx
frontend/components/popups/FolderPopup.tsx
frontend/components/popups/MetricsPopup.tsx
frontend/components/popups/PackagesPopup.tsx
frontend/components/popups/SettingsPopup.tsx
frontend/contexts/PodWebSocketContext.tsx
frontend/lib/api.ts
frontend/lib/monaco-themes.ts
frontend/lib/settings.ts
frontend/lib/themes.json
frontend/lib/websocket-native.ts
frontend/lib/websocket.ts
frontend/public/file.svg
frontend/public/globe.svg
frontend/public/next.svg
frontend/public/vercel.svg
frontend/public/window.svg
frontend/public/assets/icons/add.svg
frontend/public/assets/icons/check.svg
frontend/public/assets/icons/copy.svg
frontend/public/assets/icons/folder.svg
frontend/public/assets/icons/metric.svg
frontend/public/assets/icons/packages.svg
frontend/public/assets/icons/play.svg
frontend/public/assets/icons/python.svg
frontend/public/assets/icons/setting.svg
frontend/public/assets/icons/stop.svg
frontend/public/assets/icons/trash.svg
frontend/public/assets/icons/up-down.svg
more_compute-0.4.4.dist-info/licenses/LICENSE
more_compute-0.4.4.dist-info/METADATA
more_compute-0.4.4.dist-info/WHEEL
more_compute-0.4.4.dist-info/entry_points.txt
more_compute-0.4.4.dist-info/top_level.txt
more_compute-0.4.4.dist-info/RECORD
