Metadata-Version: 2.4
Name: more-compute
Version: 0.4.4
Summary: An interactive notebook environment for local and GPU computing
Home-page: https://github.com/DannyMang/MORECOMPUTE
Author: MoreCompute Team
Author-email: Daniel Ung <daniel.haidang.ung@gmail.com>
License: MIT
Project-URL: Homepage, https://github.com/DannyMang/MORECOMPUTE
Project-URL: Repository, https://github.com/DannyMang/MORECOMPUTE
Project-URL: Issues, https://github.com/DannyMang/MORECOMPUTE/issues
Keywords: jupyter,notebook,gpu,computing,interactive
Classifier: Development Status :: 3 - Alpha
Classifier: Intended Audience :: Developers
Classifier: License :: OSI Approved :: MIT License
Classifier: Operating System :: OS Independent
Classifier: Programming Language :: Python :: 3
Classifier: Programming Language :: Python :: 3.10
Classifier: Programming Language :: Python :: 3.11
Classifier: Programming Language :: Python :: 3.12
Requires-Python: >=3.10
License-File: LICENSE
Requires-Dist: fastapi>=0.104.0
Requires-Dist: uvicorn[standard]>=0.24.0
Requires-Dist: python-multipart>=0.0.5
Requires-Dist: nbformat>=5.0.0
Requires-Dist: click>=8.0.0
Requires-Dist: pyzmq>=25.0.0
Requires-Dist: psutil>=5.9.0
Requires-Dist: httpx>=0.24.0
Requires-Dist: cachetools>=5.3.0
Requires-Dist: matplotlib>=3.5.0
Dynamic: author
Dynamic: home-page
Dynamic: license-file
Dynamic: requires-python
